bracket_check/__init__.py
bracket_check/app/__init__.py
bracket_check/app/__main__.py
bracket_check/app/handler.py
bracket_check-0.2.0.dist-info/entry_points.txt
bracket_check-0.2.0.dist-info/WHEEL
bracket_check-0.2.0.dist-info/METADATA
bracket_check-0.2.0.dist-info/RECORD
