Metadata-Version: 2.1
Name: bracket-check
Version: 0.2.0
Summary: 
Author: skotwind
Author-email: skotwind@gmail.com
Requires-Python: >=3.7,<4.0
Classifier: Programming Language :: Python :: 3
Classifier: Programming Language :: Python :: 3.10
Classifier: Programming Language :: Python :: 3.7
Classifier: Programming Language :: Python :: 3.8
Classifier: Programming Language :: Python :: 3.9
Requires-Dist: python-shell (>=1.0.4,<2.0.0)
